logaroo/__init__.py
logaroo/console.py
logaroo/logger.py
logaroo/py.typed
logaroo-0.2.2.dist-info/licenses/LICENSE
logaroo-0.2.2.dist-info/WHEEL
logaroo-0.2.2.dist-info/METADATA
logaroo-0.2.2.dist-info/RECORD
