Metadata-Version: 2.4
Name: logaroo
Version: 0.2.2
Summary: Bouncy logging for Python
Keywords: logging
Author: Geir Arne Hjelle
Author-email: Geir Arne Hjelle <geirarne@gmail.com>
License-Expression: MIT
License-File: LICENSE
Classifier: Development Status :: 5 - Production/Stable
Classifier: Intended Audience :: Developers
Classifier: Natural Language :: English
Classifier: Operating System :: OS Independent
Classifier: Programming Language :: Python :: 3.11
Classifier: Programming Language :: Python :: 3.12
Classifier: Programming Language :: Python :: 3.13
Classifier: Programming Language :: Python :: 3
Classifier: Topic :: Software Development :: Libraries :: Python Modules
Classifier: Typing :: Typed
Requires-Dist: rich>=14.1.0 ; extra == 'rich'
Maintainer: Geir Arne Hjelle
Maintainer-email: Geir Arne Hjelle <geirarne@gmail.com>
Requires-Python: >=3.11
Project-URL: changelog, https://github.com/gahjelle/logaroo/releases
Project-URL: github, https://github.com/gahjelle/logaroo
Project-URL: homepage, https://github.com/gahjelle/logaroo
Project-URL: issues, https://github.com/gahjelle/logaroo/issues
Provides-Extra: rich
